{
    "description": "",
    "exits": {
        "down": {
            "closed": false,
            "door": true,
            "key": null,
            "locked": false,
            "secret": false,
            "to": 2004
        },
        "east": {
            "closed": false,
            "door": false,
            "key": null,
            "locked": false,
            "secret": false,
            "to": 2003
        }
    },
    "items": [],
    "mobs": [],
    "name": "La foresta elfica",
    "vnum": 2002,
    "x": 895.1328125,
    "y": 157.125
}